{
  "settings": {
    "migrated": 2,
    "iconPacksPath": ".obsidian/plugins/obsidian-icon-folder/icons",
    "fontSize": 16,
    "emojiStyle": "none",
    "iconColor": null,
    "recentlyUsedIcons": [
      "FabHeart",
      "FabAngleDown",
      "FabImage",
      "FabChessQueen",
      "FabChessKing"
    ],
    "recentlyUsedIconsSize": 5,
    "rules": [],
    "extraMargin": {
      "top": 0,
      "right": 4,
      "bottom": 0,
      "left": 0
    },
    "iconInTabsEnabled": false
  },
  "CyberSecurity - Online Learning/Certified in CyberSecurity (CC)": "FabHeart",
  "CyberSecurity - Online Learning": "FabAddressBook",
  "Cyber Security Yr1": "FabHandPeace",
  "CyberSecurity - Online Learning/HackTheBox": "FabChessRook",
  "CyberSecurity - Online Learning/Security+": "FabChessQueen",
  "CyberSecurity - Online Learning/CERTIFICATIONS.md": "FabPaperPlane",
  "General/Photos/z.images": "FabImage",
  "CyberSecurity - Online Learning/Google Cybersecurity": "FabChessKing"
}